mltkit/Display.py
mltkit/JobManager.py
mltkit/LossBuffer.py
mltkit/__init__.py
mltkit-0.3.1.dist-info/LICENSE.rst
mltkit-0.3.1.dist-info/METADATA
mltkit-0.3.1.dist-info/WHEEL
mltkit-0.3.1.dist-info/top_level.txt
mltkit-0.3.1.dist-info/RECORD
